README.txt
setup.cfg
setup.py
de9im/__init__.py
de9im/patterns.py
de9im/tests.py
de9im.egg-info/PKG-INFO
de9im.egg-info/SOURCES.txt
de9im.egg-info/dependency_links.txt
de9im.egg-info/entry_points.txt
de9im.egg-info/not-zip-safe
de9im.egg-info/top_level.txt