Metadata-Version: 1.0
Name: de9im
Version: 0.1
Summary: Dimensionally  Extended 9-Intersections Matrix utilities
Home-page: http://bitbucket.org/sgillies/de9im/
Author: Sean Gillies
Author-email: sean.gillies@gmail.com
License: BSD
Keywords: gis computational geometry
Platform: UNKNOWN
Classifier: Development Status :: 4 - Beta
Classifier: Intended Audience :: Developers
Classifier: Intended Audience :: Science/Research
Classifier: License :: OSI Approved :: BSD License
Classifier: Operating System :: OS Independent
Classifier: Programming Language :: Python
Classifier: Topic :: Scientific/Engineering :: GIS
